cerc_geometry-2.1.3.data/data/geometry/requirements.txt
cerc_geometry-2.1.3.data/data/geometry/data/geolocation/cities15000.txt
geometry/__init__.py
geometry/helper.py
geometry/library.py
geometry/location.py
geometry/map_point.py
geometry/plane.py
geometry/point.py
geometry/polygon.py
geometry/polyhedron.py
geometry/data/geolocation/cities15000.txt
cerc_geometry-2.1.3.dist-info/LICENSE.md
cerc_geometry-2.1.3.dist-info/METADATA
cerc_geometry-2.1.3.dist-info/WHEEL
cerc_geometry-2.1.3.dist-info/top_level.txt
cerc_geometry-2.1.3.dist-info/RECORD
