Metadata-Version: 2.1
Name: cerc-geometry
Version: 2.1.3
Summary: CERC Geometry Library with different modules to manipulate geometric objects
Home-page: https://nextgenerations-cities.encs.concordia.ca/gitea/p_yefi/geometry
Author: CERC
Author-email: cerc@concordia.ca
Project-URL: Repository, https://nextgenerations-cities.encs.concordia.ca/gitea/p_yefi/geometry
Project-URL: Bug Tracker, https://nextgenerations-cities.encs.concordia.ca/gitea/p_yefi/geometry/issues
Classifier: Programming Language :: Python :: 3
Classifier: License :: OSI Approved :: GNU Library or Lesser General Public License (LGPL)
Classifier: Operating System :: OS Independent
Requires-Python: >=3.6
License-File: LICENSE.md
Requires-Dist: numpy (==1.19.5)
Requires-Dist: shapely
Requires-Dist: trimesh
Requires-Dist: pathlib
Requires-Dist: pillow
Requires-Dist: setuptools
